[{"line":1,"elements":[{"line":2,"name":"I'm on the main page","description":"","type":"background","keyword":"Background","steps":[{"result":{"duration":13692522000,"status":"passed"},"line":3,"name":"Opening the browser \"https://10fastfingers.com/typing-test/russian\"","match":{"arguments":[{"val":"\"https://10fastfingers.com/typing-test/russian\"","offset":20}],"location":"stepDefinition.keyboardBot.openingTheBrowser(java.lang.String)"},"keyword":"Given "}]},{"start_timestamp":"2022-12-23T09:54:12.748Z","line":6,"name":"Bot begin testing and starting to input words","description":"","id":"bot-for-keyboard;bot-begin-testing-and-starting-to-input-words","type":"scenario","keyword":"Scenario","steps":[{"result":{"duration":79282934800,"status":"passed"},"line":7,"name":"input the marked letter","match":{"location":"stepDefinition.keyboardBot.inputLetter()"},"keyword":"When "},{"result":{"duration":733038300,"status":"passed"},"line":8,"name":"check the game is done","match":{"location":"stepDefinition.keyboardBot.checkTheGameIsDone()"},"keyword":"Then "}],"tags":[{"name":"@MyTest"}]}],"name":"Bot for keyboard","description":"","id":"bot-for-keyboard","keyword":"Feature","uri":"file:src/main/resources/Feature/bot.feature","tags":[]}]